iArt/__init__.py
iArt/iArt.py
python_iArt-1.1.3.dist-info/LICENSE
python_iArt-1.1.3.dist-info/METADATA
python_iArt-1.1.3.dist-info/WHEEL
python_iArt-1.1.3.dist-info/top_level.txt
python_iArt-1.1.3.dist-info/RECORD
