Metadata-Version: 2.1
Name: python-iArt
Version: 1.1.3
Summary: iArt: A Generalized Framework for Imputation-Assisted Randomization Tests
Home-page: https://github.com/Imputation-Assisted-Randomization-Tests/iArt-py
Author: Siyu Heng, Jiawei Zhang, and Yang Feng
Author-email: siyuheng@nyu.edu,jz4721@nyu.edu,yang.feng@nyu.edu
License: UNKNOWN
Platform: UNKNOWN
Classifier: Development Status :: 3 - Alpha
Classifier: Intended Audience :: Developers
Classifier: License :: OSI Approved :: MIT License
Classifier: Programming Language :: Python :: 3
Classifier: Programming Language :: Python :: 3.8
Requires-Python: >=3.8
Requires-Dist: mv-laplace
Requires-Dist: pandas
Requires-Dist: numpy
Requires-Dist: scikit-learn
Requires-Dist: xgboost
Requires-Dist: statsmodels
Requires-Dist: lightgbm
